virtual/__init__.py
virtual/btrblocks_utils.py
virtual/data_handler.py
virtual/expr_optimizer.py
virtual/expr_parser.py
virtual/interface.py
virtual/io_utils.py
virtual/utils.py
virtual/v_compressor.py
virtual/v_driller.py
virtual/v_optimizer.py
virtual/v_reconstructor.py
virtual/v_size.py
virtual/models/k_regression.py
virtual/models/sparse_model.py
virtual/schema_inference/__init__.py
virtual/schema_inference/heavyweight_schema_inference.py
virtual/schema_inference/lightweight_schema_inference.py
virtual/schema_inference/schema_utils.py
virtual_parquet-0.2.2.dist-info/licenses/LICENSE
virtual_parquet-0.2.2.dist-info/METADATA
virtual_parquet-0.2.2.dist-info/WHEEL
virtual_parquet-0.2.2.dist-info/top_level.txt
virtual_parquet-0.2.2.dist-info/RECORD
