Metadata-Version: 2.4
Name: virtual-parquet
Version: 0.2.2
Summary: 🗜️Compressing Parquet files using functions
Author-email: UTN Data Systems Lab <data-systems@utn.de>
License: MIT License
Project-URL: Homepage, https://github.com/utndatasystems/virtual
Project-URL: Issues, https://github.com/utndatasystems/virtual/issues
Keywords: correlation-aware compression,semantic compression
Classifier: Programming Language :: Python :: 3
Classifier: License :: OSI Approved :: MIT License
Classifier: Operating System :: OS Independent
License-File: LICENSE
Requires-Dist: pandas
Requires-Dist: duckdb
Requires-Dist: pyarrow
Requires-Dist: pyyaml
Requires-Dist: scikit-learn
Dynamic: license-file
